input_with_timeout/__init__.py
input_with_timeout/__version__.py
input_with_timeout/console_output.py
input_with_timeout/main.py
input_with_timeout-2.2.dist-info/LICENSE
input_with_timeout-2.2.dist-info/METADATA
input_with_timeout-2.2.dist-info/WHEEL
input_with_timeout-2.2.dist-info/top_level.txt
input_with_timeout-2.2.dist-info/RECORD
