Metadata-Version: 2.1
Name: input-with-timeout
Version: 2.2
Summary: The 'input-with-timeout' module provides a cross-platform method to capture user input with a timeout feature.
Home-page: http://github.com/mamahoos/input_with_timeout
Author: mamahoos
Author-email: m4m4hoos@gmail.com
License: MIT License
Keywords: python,cross-platform,stdout,stin,console
Classifier: Development Status :: 5 - Production/Stable
Classifier: Intended Audience :: Developers
Classifier: License :: OSI Approved :: MIT License
Classifier: Programming Language :: Python
Classifier: Programming Language :: Python :: 3
Classifier: Operating System :: OS Independent
License-File: LICENSE
